{
  "24 AYAR": {
    "alış": "----",
    "satış": "4.260"
  },
  "22 AYAR": {
    "alış": "3.860",
    "satış": "4.240"
  },
  "14 AYAR": {
    "alış": "----",
    "satış": "3.760"
  },
  "BEŞLİ": {
    "alış": "140.250",
    "satış": "143.250"
  },
  "TAM": {
    "alış": "28.050",
    "satış": "28.650"
  },
  "YARIM": {
    "alış": "13.580",
    "satış": "13.880"
  },
  "ÇEYREK": {
    "alış": "6.790",
    "satış": "6.940"
  },
  "24 AYAR 1 GRAM": {
    "alış": "4.185",
    "satış": "4.335"
  },
  "guncellemeZamani": "01.07.2025 05:16:28"
}