{
  "24 AYAR": {
    "alış": "----",
    "satış": "4.240"
  },
  "22 AYAR": {
    "alış": "3.850",
    "satış": "4.220"
  },
  "14 AYAR": {
    "alış": "----",
    "satış": "3.740"
  },
  "BEŞLİ": {
    "alış": "140.000",
    "satış": "143.000"
  },
  "TAM": {
    "alış": "28.000",
    "satış": "28.600"
  },
  "YARIM": {
    "alış": "13.580",
    "satış": "13.880"
  },
  "ÇEYREK": {
    "alış": "6.790",
    "satış": "6.940"
  },
  "24 AYAR 1 GRAM": {
    "alış": "4.165",
    "satış": "4.315"
  },
  "guncellemeZamani": "27.06.2025 18:34:24"
}